<?xml version="1.0" encoding="utf-8"?>
<!-- $Revision$ -->
<!-- EN-Revision: 9906c5636517caee19cad1cc65e37fdf32473d55 Maintainer: takagi Status: ready -->
<itemizedlist xmlns="http://docbook.org/ns/docbook"
xmlns:xlink="http://www.w3.org/1999/xlink">
 <listitem>
  <para>
   &null;。この場合はデフォルトのタイムゾーンを使います。デフォルトは、ini 項目
   <link linkend="ini.date.timezone">date.timezone</link> で設定したものか、
   <function>date_default_timezone_set</function> 関数で指定したもの
   (そして <function>date_default_timezone_get</function> が返すもの) になります。
  </para>
 </listitem>
 <listitem>
  <para>
   <classname>IntlTimeZone</classname>。これを直接使います。
  </para>
 </listitem>
 <listitem>
  <para>
   <classname>DateTimeZone</classname>。その識別子を取り出して、ICU タイムゾーンオブジェクトを作ります。
   つまり、これは ICU のデータベースに基づくタイムゾーンとなり、PHP のタイムゾーンデータベースに基づくものではありません。
  </para>
 </listitem>
 <listitem>
  <para>
   文字列。ICU タイムゾーン識別子として有効なものを指定します。
   <function>IntlTimeZone::createTimeZoneIDEnumeration</function> を参照ください。
   <literal>"GMT+08:30"</literal> などのオフセットも指定できます。
  </para>
 </listitem>
</itemizedlist>
